osis_python-0.1.4.dist-info/licenses/LICENSE
pyosis/__init__.py
pyosis/ai/__init__.py
pyosis/ai/agents/BaseAgent.py
pyosis/ai/agents/DecisionAgent.py
pyosis/ai/agents/MaterialAgent.py
pyosis/ai/agents/ModelAgent.py
pyosis/ai/agents/QuickBuildingAgent.py
pyosis/ai/agents/SectionAgent.py
pyosis/ai/agents/__init__.py
pyosis/boundary/__init__.py
pyosis/boundary/interface.py
pyosis/control/__init__.py
pyosis/control/interface.py
pyosis/core/PyInterface.pyi
pyosis/core/__init__.py
pyosis/core/command.py
pyosis/core/engine.py
pyosis/element/__init__.py
pyosis/element/interface.py
pyosis/general/__init__.py
pyosis/general/interface.py
pyosis/live/__init__.py
pyosis/live/analysis.py
pyosis/live/grade.py
pyosis/live/lane.py
pyosis/load/__init__.py
pyosis/load/loadcase.py
pyosis/load/static.py
pyosis/load/tendon.py
pyosis/material/__init__.py
pyosis/material/interface.py
pyosis/node/__init__.py
pyosis/node/interface.py
pyosis/post/__init__.py
pyosis/post/interface.py
pyosis/property/__init__.py
pyosis/property/coordinate.py
pyosis/property/creep_shrink.py
pyosis/property/damping.py
pyosis/property/pu_curve.py
pyosis/quick_building/__init__.py
pyosis/quick_building/interface.py
pyosis/section/__init__.py
pyosis/section/common.py
pyosis/section/numeric.py
pyosis/section/param.py
pyosis/section/steel.py
pyosis/stage/__init__.py
pyosis/stage/define.py
pyosis/stage/overall.py
osis_python-0.1.4.dist-info/METADATA
osis_python-0.1.4.dist-info/WHEEL
osis_python-0.1.4.dist-info/top_level.txt
osis_python-0.1.4.dist-info/RECORD
