Metadata-Version: 2.4
Name: osis-python
Version: 0.1.4
Summary: A Python client library for Osis APDL
Author-email: "CCCC Highway Consultant Co. Ltd." <support@osisbim.com>
License: MIT License
Project-URL: Homepage, https://github.com/osis-ai/pyosis
Project-URL: Documentation, https://github.com/osis-ai/pyosis#readme
Project-URL: Repository, https://github.com/osis-ai/pyosis.git
Project-URL: BugTracker, https://github.com/osis-ai/pyosis/issues
Classifier: Development Status :: 4 - Beta
Classifier: Intended Audience :: Developers
Classifier: Topic :: Software Development :: Libraries
Classifier: License :: OSI Approved :: MIT License
Classifier: Programming Language :: Python :: 3
Classifier: Programming Language :: Python :: 3.11
Classifier: Programming Language :: Python :: 3.12
Requires-Python: >=3.11
License-File: LICENSE
Requires-Dist: langchain>=1.0.3
Requires-Dist: langchain-core>=1.0.3
Requires-Dist: langchain-openai>=1.0.2
Requires-Dist: pydantic>=2.12.4
Requires-Dist: pydantic_core>=2.41.5
Provides-Extra: dev
Requires-Dist: pytest>=7.0; extra == "dev"
Requires-Dist: black>=23.0; extra == "dev"
Requires-Dist: mypy>=1.0; extra == "dev"
Provides-Extra: test
Requires-Dist: pytest>=7.0; extra == "test"
Requires-Dist: pytest-cov>=4.0; extra == "test"
Dynamic: license-file
